<annotation>
	<folder>Mancal Schulz DRIVE</folder>
	<filename>IMG_20200901_153731.jpg</filename>
	<path>C:\Users\dougl\Documents\Yonface\Articfox\Labelmg\Mancal Schulz DRIVE\IMG_20200901_153731.jpg</path>
	<source>
		<database>Unknown</database>
	</source>
	<size>
		<width>3000</width>
		<height>3000</height>
		<depth>3</depth>
	</size>
	<segmented>0</segmented>
	<object>
		<name>buraco</name>
		<pose>Unspecified</pose>
		<truncated>0</truncated>
		<difficult>0</difficult>
		<bndbox>
			<xmin>1572</xmin>
			<ymin>1289</ymin>
			<xmax>1614</xmax>
			<ymax>1344</ymax>
		</bndbox>
	</object>
	<object>
		<name>buraco</name>
		<pose>Unspecified</pose>
		<truncated>0</truncated>
		<difficult>0</difficult>
		<bndbox>
			<xmin>1524</xmin>
			<ymin>1376</ymin>
			<xmax>1618</xmax>
			<ymax>1512</ymax>
		</bndbox>
	</object>
	<object>
		<name>buraco</name>
		<pose>Unspecified</pose>
		<truncated>0</truncated>
		<difficult>0</difficult>
		<bndbox>
			<xmin>1572</xmin>
			<ymin>1583</ymin>
			<xmax>1608</xmax>
			<ymax>1622</ymax>
		</bndbox>
	</object>
</annotation>
